Metadata-Version: 1.1
Name: MaildropccReader
Version: 1.1.0
Summary: Simple API to extract emails of accounts from www.maildrop.cc
Home-page: https://github.com/rtorres90/maildropcc-reader
Author: Roberto Torres
Author-email: roberto.torres.dev@gmail.com
License: UNKNOWN
Download-URL: https://github.com/rtorres90/maildropcc-reader/archive/1.1.0.tar.gz
Keywords: api,maildropcc,testing
Platform: UNKNOWN
Classifier: Programming Language :: Python :: 2.7
